ezmonitor/__init__.py
ezmonitor/main.py
ezmonitor/src.py
ezmonitor/utils.py
ezmonitor/version.py
ezmonitor-1.0.3.dist-info/METADATA
ezmonitor-1.0.3.dist-info/WHEEL
ezmonitor-1.0.3.dist-info/entry_points.txt
ezmonitor-1.0.3.dist-info/top_level.txt
ezmonitor-1.0.3.dist-info/RECORD
