Metadata-Version: 2.1
Name: ezmonitor
Version: 1.0.3
Summary: UNKNOWN
Home-page: https://github.com/yodeng/ezmonitor
Author-email: yodeng@tju.edu.cn
License: BSD
Platform: UNKNOWN
Requires-Python: >=2.7.10, <3.10
Requires-Dist: matplotlib
Requires-Dist: psutil
Requires-Dist: pandas
Requires-Dist: numpy
